omitme/__init__.py
omitme/__main__.py
omitme/cli/__init__.py
omitme/errors.py
omitme/gui/app.py
omitme/platforms/__init__.py
omitme/platforms/discord.py
omitme/platforms/element.py
omitme/platforms/matrix.py
omitme/platforms/reddit.py
omitme/platforms/twitter.py
omitme/resources/__init__.py
omitme/resources/omitme.icns
omitme/resources/omitme.ico
omitme/resources/omitme.png
omitme/resources/platforms/discord.png
omitme/resources/platforms/element.png
omitme/resources/platforms/matrix.png
omitme/resources/platforms/reddit.png
omitme/util/accounts.py
omitme/util/events.py
omitme/util/platform.py
omitme/util/targets.py
omitme/util/wait_for.py
omitme-0.0.9.dist-info/LICENSE
omitme-0.0.9.dist-info/METADATA
omitme-0.0.9.dist-info/WHEEL
omitme-0.0.9.dist-info/entry_points.txt
omitme-0.0.9.dist-info/RECORD
