Metadata-Version: 2.1
Name: omitme
Version: 0.0.9
Summary: OmitMe - Your Privacy-Centric, Easily Extendable Data Deletion Solution
License: GNU General Public License v3 (GPLv3)
Author: WardPearce
Author-email: wardpearce@pm.me
Requires-Python: >=3.10,<3.12
Classifier: License :: Other/Proprietary License
Classifier: Programming Language :: Python :: 3
Classifier: Programming Language :: Python :: 3.10
Classifier: Programming Language :: Python :: 3.11
Requires-Dist: aiofiles (>=23.2.1,<24.0.0)
Requires-Dist: click (>=8.1.7,<9.0.0)
Requires-Dist: cryptography (>=41.0.3,<43.0.0)
Requires-Dist: httpx (>=0.24.1,<0.28.0)
Requires-Dist: keyring[completion] (>=24.2,<26.0)
Requires-Dist: pydantic (>=2.1.1,<3.0.0)
Requires-Dist: selenium (>=4.11.2,<5.0.0)
Requires-Dist: selenium-wire (>=5.1.0,<6.0.0)
Requires-Dist: setuptools (>=68.2.2,<70.0.0)
Requires-Dist: yarl (>=1.9.2,<2.0.0)
